ansys/scade/almgw_sphinx_needs/__init__.py
ansys/scade/almgw_sphinx_needs/almgw_sphinx_needs.properties
ansys/scade/almgw_sphinx_needs/almgw_sphinx_needs.srg
ansys/scade/almgw_sphinx_needs/almgw_sphinx_needs23r1.srg
ansys/scade/almgw_sphinx_needs/almgw_sphinx_needs24r1.srg
ansys/scade/almgw_sphinx_needs/export.py
ansys/scade/almgw_sphinx_needs/needs.py
ansys/scade/almgw_sphinx_needs/options.py
ansys/scade/almgw_sphinx_needs/reggitext2.ps1
ansys/scade/almgw_sphinx_needs/register.py
ansys/scade/almgw_sphinx_needs/settings.py
ansys/scade/almgw_sphinx_needs/setup.py
ansys/scade/almgw_sphinx_needs/sphinx_needs.py
ansys/scade/almgw_sphinx_needs/trace.py
ansys/scade/almgw_sphinx_needs/unregister.py
ansys/scade/almgw_sphinx_needs/res/_null.png
ansys/scade/almgw_sphinx_needs/res/sphinx-needs.bmp
ansys_scade_almgw_sphinx_needs-0.3.0.dist-info/entry_points.txt
ansys_scade_almgw_sphinx_needs-0.3.0.dist-info/licenses/LICENSE
ansys_scade_almgw_sphinx_needs-0.3.0.dist-info/WHEEL
ansys_scade_almgw_sphinx_needs-0.3.0.dist-info/METADATA
ansys_scade_almgw_sphinx_needs-0.3.0.dist-info/RECORD
